[{"user": 7, "amount": "3200.00", "method": "m-pesa", "reference": "ERTQR13", "created_at": "2025-04-15 01:12:55"}, {"user": 6, "amount": "5600.00", "method": "Bank", "reference": "ERTOP12", "created_at": "2025-04-15 01:12:55"}, {"user": 5, "amount": "2100.00", "method": "Cash", "reference": "--", "created_at": "2025-04-15 01:12:55"}, {"user": 4, "amount": "3800.00", "method": "m-pesa", "reference": "ERTMN01", "created_at": "2025-04-15 01:12:55"}, {"user": 3, "amount": "1456.00", "method": "Bank", "reference": "ERTJK90", "created_at": "2025-04-15 01:12:55"}, {"user": 2, "amount": "2750.00", "method": "Cash", "reference": "--", "created_at": "2025-04-15 01:12:55"}, {"user": 1, "amount": "1920.00", "method": "m-pesa", "reference": "ERTGH78", "created_at": "2025-04-15 01:12:55"}, {"user": 10, "amount": "2380.00", "method": "m-pesa", "reference": "ETRGE46G", "created_at": "2025-04-15 01:10:28"}]